Metadata-Version: 1.1
Name: textwriter
Version: 0.0.3
Summary: A basic text writer
Home-page: UNKNOWN
Author: Joaf
Author-email: admin@jfncgamerinc.com
License: MIT
Keywords: textwriter
Platform: UNKNOWN
Classifier: Development Status :: 5 - Production/Stable
Classifier: Intended Audience :: Education
Classifier: Operating System :: Microsoft :: Windows :: Windows 10
Classifier: License :: OSI Approved :: MIT License
Classifier: Programming Language :: Python :: 3
